zmp_manual_backend/__init__.py
zmp_manual_backend/api/__init__.py
zmp_manual_backend/api/auth_router.py
zmp_manual_backend/api/manual_router.py
zmp_manual_backend/api/oauth2_keycloak.py
zmp_manual_backend/core/__init__.py
zmp_manual_backend/core/auth_service.py
zmp_manual_backend/core/knowledge_store_mcp_client.py
zmp_manual_backend/core/manual_service.py
zmp_manual_backend/main.py
zmp_manual_backend/models/__init__.py
zmp_manual_backend/models/auth.py
zmp_manual_backend/models/auth_schema.py
zmp_manual_backend/models/manual.py
zmp_manual_backend/models/user.py
zmp_manual_backend/services/__init__.py
zmp_manual_backend-0.4.4.dist-info/LICENSE
zmp_manual_backend-0.4.4.dist-info/METADATA
zmp_manual_backend-0.4.4.dist-info/WHEEL
zmp_manual_backend-0.4.4.dist-info/RECORD
