Metadata-Version: 2.3
Name: zmp-manual-backend
Version: 0.4.4
Summary: Backend service for ZMP manual management
Author: stiron
Author-email: lesch1@gmail.com
Requires-Python: >=3.11,<4.0
Classifier: Programming Language :: Python :: 3
Classifier: Programming Language :: Python :: 3.11
Classifier: Programming Language :: Python :: 3.12
Classifier: Programming Language :: Python :: 3.13
Requires-Dist: aiofiles (>=24.1.0,<25.0.0)
Requires-Dist: asyncio (>=3.4.3,<4.0.0)
Requires-Dist: boto3 (>=1.39.3,<2.0.0)
Requires-Dist: colorlog (>=6.9.0,<7.0.0)
Requires-Dist: cryptography (>=44.0.2,<45.0.0)
Requires-Dist: deepl (>=1.21.1,<2.0.0)
Requires-Dist: fastapi (>=0.110.0,<0.111.0)
Requires-Dist: fastmcp (>=2.9.2,<3.0.0)
Requires-Dist: gitpython (>=3.1.44,<4.0.0)
Requires-Dist: itsdangerous (>=2.1.2,<3.0.0)
Requires-Dist: passlib[bcrypt] (>=1.7.4,<2.0.0)
Requires-Dist: pillow (>=10.2.0,<11.0.0)
Requires-Dist: pydantic[email] (>=2.10.6,<3.0.0)
Requires-Dist: pyjwt[crypto] (>=2.10.1,<3.0.0)
Requires-Dist: python-dotenv (>=1.0.1,<2.0.0)
Requires-Dist: python-multipart (>=0.0.9,<0.0.10)
Requires-Dist: requests (>=2.31.0,<3.0.0)
Requires-Dist: sse-starlette (>=1.8.2,<2.0.0)
Requires-Dist: starlette-csrf (>=1.4.4,<2.0.0)
Requires-Dist: uvicorn (>=0.27.1,<0.28.0)
Requires-Dist: zmp-md-translator (==0.2.8)
Requires-Dist: zmp-notion-exporter (>=0.3.7,<0.4.0)
